{
  "title": "МАТЕМАТИКА И КУЛЬТУРА: УНИКАЛЬНОСТЬ И УНИВЕРСАЛЬНОСТЬ МАТЕМАТИКИ\nТекст научной статьи по специальности «Философия, этика, религиоведение»",
  "url": "https://cyberleninka.ru/article/n/matematika-i-kultura-unikalnost-i-universalnost-matematiki",
  "filename": "01_МАТЕМАТИКА И КУЛЬТУРА_ УНИКАЛЬНОСТЬ И УНИВЕРСАЛЬНО",
  "files": {
    "original": "01_МАТЕМАТИКА И КУЛЬТУРА_ УНИКАЛЬНОСТЬ И УНИВЕРСАЛЬНО.pdf",
    "text": "01_МАТЕМАТИКА И КУЛЬТУРА_ УНИКАЛЬНОСТЬ И УНИВЕРСАЛЬНО.txt",
    "summary": "01_МАТЕМАТИКА И КУЛЬТУРА_ УНИКАЛЬНОСТЬ И УНИВЕРСАЛЬНО_sh.txt",
    "annotation": "01_МАТЕМАТИКА И КУЛЬТУРА_ УНИКАЛЬНОСТЬ И УНИВЕРСАЛЬНО_an.txt"
  }
}